setup.py
docs/INSTALL.txt
docs/LICENSE.GPL
docs/LICENSE.txt
plonehrm/__init__.py
plonehrm.jobperformance.egg-info/PKG-INFO
plonehrm.jobperformance.egg-info/SOURCES.txt
plonehrm.jobperformance.egg-info/dependency_links.txt
plonehrm.jobperformance.egg-info/entry_points.txt
plonehrm.jobperformance.egg-info/namespace_packages.txt
plonehrm.jobperformance.egg-info/not-zip-safe
plonehrm.jobperformance.egg-info/requires.txt
plonehrm.jobperformance.egg-info/top_level.txt
plonehrm/jobperformance/HISTORY.txt
plonehrm/jobperformance/README.txt
plonehrm/jobperformance/TODO.txt
plonehrm/jobperformance/__init__.py
plonehrm/jobperformance/config.py
plonehrm/jobperformance/configure.zcml
plonehrm/jobperformance/deprecation.zcml
plonehrm/jobperformance/events.py
plonehrm/jobperformance/interfaces.py
plonehrm/jobperformance/permissions.zcml
plonehrm/jobperformance/rebuild_i18n.sh
plonehrm/jobperformance/tool.gif
plonehrm/jobperformance/tool.py
plonehrm/jobperformance/version.txt
plonehrm/jobperformance/browser/__init__.py
plonehrm/jobperformance/browser/configure.zcml
plonehrm/jobperformance/browser/improvement_areas.pt
plonehrm/jobperformance/browser/improvement_edit.pt
plonehrm/jobperformance/browser/improvement_view.pt
plonehrm/jobperformance/browser/interfaces.py
plonehrm/jobperformance/browser/interview.pt
plonehrm/jobperformance/browser/jobperformance.kss
plonehrm/jobperformance/browser/jobperformance.pt
plonehrm/jobperformance/browser/jobperformance.py
plonehrm/jobperformance/content/__init__.py
plonehrm/jobperformance/content/jobperformance.py
plonehrm/jobperformance/doc/__init__.py
plonehrm/jobperformance/doc/overview.txt
plonehrm/jobperformance/locales/jobperformance.pot
plonehrm/jobperformance/locales/en/LC_MESSAGES/jobperformance.po
plonehrm/jobperformance/locales/nl/LC_MESSAGES/jobperformance.po
plonehrm/jobperformance/locales/pt_BR/LC_MESSAGES/jobperformance.po
plonehrm/jobperformance/profiles/default/actionicons.xml
plonehrm/jobperformance/profiles/default/controlpanel.xml
plonehrm/jobperformance/profiles/default/factorytool.xml
plonehrm/jobperformance/profiles/default/kssregistry.xml
plonehrm/jobperformance/profiles/default/propertiestool.xml
plonehrm/jobperformance/profiles/default/rolemap.xml
plonehrm/jobperformance/profiles/default/toolset.xml
plonehrm/jobperformance/profiles/default/types.xml
