Metadata-Version: 1.0
Name: plonehrm.jobperformance
Version: 1.2.1
Summary: Job performance interviews for Plone HRM.
Home-page: http://svn.plone.org/svn/collective/plonehrm.jobperformance
Author: Jean-Paul Ladage
Author-email: j.ladage@zestsoftware.nl
License: GPL
Keywords: hrm
Platform: UNKNOWN
Classifier: Framework :: Plone
Classifier: Framework :: Zope2
Classifier: Framework :: Zope3
Classifier: Programming Language :: Python
Classifier: Topic :: Software Development :: Libraries :: Python Modules
